docs/api-reference/advanced/common.md
docs/api-reference/advanced/exporters.md
docs/api-reference/advanced/recorders.md
docs/api-reference/cli.md
docs/api-reference/models.md
docs/api-reference/README.md
docs/api-reference/record.md
harlem/__init__.py
harlem/__main__.py
harlem/cli.py
harlem/common.py
harlem/exporters/__init__.py
harlem/exporters/base.py
harlem/exporters/common.py
harlem/exporters/composite_exporter.py
harlem/exporters/concurrent_exporter.py
harlem/exporters/io_exporter.py
harlem/exporters/live_file_exporter.py
harlem/exporters/logging_exporter.py
harlem/exporters/model_exporter.py
harlem/models/__init__.py
harlem/models/har.py
harlem/py.typed
harlem/record.py
harlem/recorders/__init__.py
harlem/recorders/aiohttp_recorder.py
harlem/recorders/base.py
harlem/recorders/common.py
harlem/recorders/composite_recorder.py
harlem/recorders/requests_recorder.py
harlem-0.2.0a2.dist-info/entry_points.txt
harlem-0.2.0a2.dist-info/LICENSE
harlem-0.2.0a2.dist-info/METADATA
harlem-0.2.0a2.dist-info/WHEEL
harlem-0.2.0a2.dist-info/RECORD
