Metadata-Version: 2.1
Name: harlem
Version: 0.2.0a2
Summary: Powerful, simple, Python HAR (HTTP Archive) recorder and exporter.
Home-page: https://github.com/WolfDWyc/harlem
License: AGPL-3.0-or-later
Author: WolfDWyc
Author-email: 62406166+WolfDWyc@users.noreply.github.com
Requires-Python: >=3.8,<4.0
Classifier: License :: OSI Approved :: GNU Affero General Public License v3 or later (AGPLv3+)
Classifier: Programming Language :: Python :: 3
Classifier: Programming Language :: Python :: 3.8
Classifier: Programming Language :: Python :: 3.9
Classifier: Programming Language :: Python :: 3.10
Classifier: Programming Language :: Python :: 3.11
Requires-Dist: aiohttp (==3.8.5)
Requires-Dist: click (>=8.1.7,<9.0.0)
Requires-Dist: pydantic (>=2.6.4,<3.0.0)
Requires-Dist: requests (>=2.31.0,<3.0.0)
Requires-Dist: yarl (>=1.9.4,<2.0.0)
